lekcut/__init__.py
lekcut/deepcut.py
lekcut/model/__init__.py
lekcut/model/deepcut.onnx
LEKCut-0.1.dist-info/LICENSE
LEKCut-0.1.dist-info/METADATA
LEKCut-0.1.dist-info/WHEEL
LEKCut-0.1.dist-info/top_level.txt
LEKCut-0.1.dist-info/RECORD
