Metadata-Version: 2.1
Name: LEKCut
Version: 0.1
Summary: LEKCut (เล็ก คัด) is a Thai tokenization library that ports the deep learning model to the onnx model.
Home-page: https://github.com/PyThaiNLP/LEKCut
Author: Wannaphong Phatthiyaphaibun
Author-email: wannaphong@yahoo.com
License: Apache Software License 2.0
Project-URL: Source, https://github.com/PyThaiNLP/LEKCut
Project-URL: Bug Reports, https://github.com/PyThaiNLP/LEKCut/issues
Keywords: thai,NLP,natural language processing,text analytics,text processing,localization,computational linguistics,Thai language
Classifier: Development Status :: 3 - Alpha
Classifier: Programming Language :: Python :: 3
Classifier: Intended Audience :: Developers
Classifier: License :: OSI Approved :: Apache Software License
Classifier: Topic :: Scientific/Engineering :: Artificial Intelligence
Classifier: Topic :: Text Processing
Classifier: Topic :: Text Processing :: General
Classifier: Topic :: Text Processing :: Linguistic
Requires-Python: >=3.6
License-File: LICENSE
Requires-Dist: numpy
Requires-Dist: onnxruntime
Requires-Dist: onnx
